{
  "courses": [
    {
      "id": "1",
      "title": "Postman",
      "Descrption": "full Postman course from zero in arabic",
      "Author": "khaled bedoui",
      "isActive": true,
      "videos": [
        {
          "id": 1,
          "title": "Postman Introduction",
          "url": "https://youtube.com"
        },
        {
          "id": 2,
          "title": "Postman installation",
          "url": "https://youtube.com"
        }
      ]
    },
    {
      "id": "2",
      "title": "selenium",
      "Descrption": "full selenium course from zero in arabic",
      "Author": "khaled bedoui",
      "isActive": false,
      "videos": [
        {
          "id": 1,
          "title": "selenium Introduction",
          "url": "https://youtube.com"
        },
        {
          "id": 2,
          "title": "selenium installation",
          "url": "https://youtube.com"
        }
      ]
    },
    {
      "id": "3",
      "title": "cypress",
      "Descrption": "full cypress course from zero in arabic"
    }
  ],
  "users": [
    {
      "id": "1",
      "frisname": "Hatem"
    }
  ]
}